mricloudpy/__init__.py
mricloudpy/access.py
mricloudpy/analysis.py
mricloudpy/data.py
mricloudpy/imaging.py
mricloudpy/read.py
mricloudpy/visuals.py
mricloudpy/resources/JHU_MNI_SS_T1.nii.gz
mricloudpy/resources/multilevel_lookup_table.txt
mricloudpy-0.0.1.dist-info/LICENSE.txt
mricloudpy-0.0.1.dist-info/METADATA
mricloudpy-0.0.1.dist-info/WHEEL
mricloudpy-0.0.1.dist-info/top_level.txt
mricloudpy-0.0.1.dist-info/RECORD
