Metadata-Version: 2.1
Name: mricloudpy
Version: 0.0.1
Summary: A package for handling MRICloud output data
Project-URL: Homepage, https://github.com/MR-Biomarker-Resource/mricloudpy
Project-URL: Documentation, https://mr-biomarker-resource.github.io/mricloudpy/
Classifier: Programming Language :: Python :: 3
Classifier: License :: OSI Approved :: MIT License
Classifier: Operating System :: OS Independent
Requires-Python: >=3.8
License-File: LICENSE.txt
Requires-Dist: pandas
Requires-Dist: numpy
Requires-Dist: nibabel
Requires-Dist: plotly
Requires-Dist: plotly-express
Requires-Dist: statsmodels
Requires-Dist: scikit-learn
Requires-Dist: scipy
